PyMVPA/__init__.py
PyMVPA/_random.py
PyMVPA/suite.py
PyMVPA/tutorial_suite.py
PyMVPA/algorithms/__init__.py
PyMVPA/algorithms/connectivity_hyperalignment.py
PyMVPA/algorithms/group_clusterthr.py
PyMVPA/algorithms/hyperalignment.py
PyMVPA/algorithms/searchlight_hyperalignment.py
PyMVPA/algorithms/benchmarks/__init__.py
PyMVPA/algorithms/benchmarks/hyperalignment.py
PyMVPA/atlases/__init__.py
PyMVPA/atlases/base.py
PyMVPA/atlases/fsl.py
PyMVPA/atlases/transformation.py
PyMVPA/atlases/warehouse.py
PyMVPA/base/__init__.py
PyMVPA/base/attributes.py
PyMVPA/base/collections.py
PyMVPA/base/config.py
PyMVPA/base/constraints.py
PyMVPA/base/dataset.py
PyMVPA/base/dochelpers.py
PyMVPA/base/externals.py
PyMVPA/base/hdf5.py
PyMVPA/base/info.py
PyMVPA/base/learner.py
PyMVPA/base/node.py
PyMVPA/base/param.py
PyMVPA/base/progress.py
PyMVPA/base/report.py
PyMVPA/base/report_dummy.py
PyMVPA/base/state.py
PyMVPA/base/types.py
PyMVPA/base/verbosity.py
PyMVPA/clfs/__init__.py
PyMVPA/clfs/_svmbase.py
PyMVPA/clfs/base.py
PyMVPA/clfs/blr.py
PyMVPA/clfs/distance.py
PyMVPA/clfs/dummies.py
PyMVPA/clfs/enet.py
PyMVPA/clfs/gda.py
PyMVPA/clfs/glmnet.py
PyMVPA/clfs/gnb.py
PyMVPA/clfs/gpr.py
PyMVPA/clfs/knn.py
PyMVPA/clfs/lars.py
PyMVPA/clfs/mass.py
PyMVPA/clfs/meta.py
PyMVPA/clfs/model_selector.py
PyMVPA/clfs/plr.py
PyMVPA/clfs/ridge.py
PyMVPA/clfs/similarity.py
PyMVPA/clfs/smlr.py
PyMVPA/clfs/stats.py
PyMVPA/clfs/svm.py
PyMVPA/clfs/transerror.py
PyMVPA/clfs/warehouse.py
PyMVPA/clfs/libsmlrc/__init__.py
PyMVPA/clfs/libsmlrc/ctypes_helper.py
PyMVPA/clfs/libsvmc/__init__.py
PyMVPA/clfs/libsvmc/_svm.py
PyMVPA/clfs/libsvmc/sens.py
PyMVPA/clfs/libsvmc/svm.py
PyMVPA/clfs/sg/__init__.py
PyMVPA/clfs/sg/sens.py
PyMVPA/clfs/sg/svm.py
PyMVPA/clfs/skl/__init__.py
PyMVPA/clfs/skl/base.py
PyMVPA/cmdline/__init__.py
PyMVPA/cmdline/cmd_atlaslabeler.py
PyMVPA/cmdline/cmd_crossval.py
PyMVPA/cmdline/cmd_describe.py
PyMVPA/cmdline/cmd_dump.py
PyMVPA/cmdline/cmd_exec.py
PyMVPA/cmdline/cmd_hyperalign.py
PyMVPA-4.0.0.dist-info/COPYING
PyMVPA-4.0.0.dist-info/METADATA
PyMVPA-4.0.0.dist-info/WHEEL
PyMVPA-4.0.0.dist-info/top_level.txt
PyMVPA-4.0.0.dist-info/RECORD
